tagcloud/__init__.py
tagcloud/templatetags/__init__.py
tagcloud/templatetags/tagcloud.py
tagcloud/templates/tagcloud/tagcloud.html
django_tagcloud-0.1.1.dist-info/top_level.txt
django_tagcloud-0.1.1.dist-info/METADATA
django_tagcloud-0.1.1.dist-info/DESCRIPTION.rst
django_tagcloud-0.1.1.dist-info/metadata.json
django_tagcloud-0.1.1.dist-info/WHEEL
django_tagcloud-0.1.1.dist-info/RECORD
