Metadata-Version: 2.0
Name: django-tagcloud
Version: 0.1.1
Summary: A simple Django templatetag for generating tagclouds
Home-page: https://github.com/sjkingo/django_tagcloud
Author: Sam Kingston
Author-email: sam@sjkwi.com.au
License: BSD
Platform: UNKNOWN
Classifier: Development Status :: 5 - Production/Stable
Classifier: Environment :: Web Environment
Classifier: Framework :: Django
Classifier: Intended Audience :: Developers
Classifier: License :: OSI Approved :: BSD License
Requires-Dist: Django
